otazkovac/helpers.py
otazkovac/__init__.py
otazkovac-0.0.1.dist-info/entry_points.txt
otazkovac-0.0.1.dist-info/DESCRIPTION.rst
otazkovac-0.0.1.dist-info/WHEEL
otazkovac-0.0.1.dist-info/METADATA
otazkovac-0.0.1.dist-info/RECORD
otazkovac-0.0.1.dist-info/metadata.json
otazkovac-0.0.1.dist-info/top_level.txt
