Metadata-Version: 2.0
Name: otazkovac
Version: 0.0.1
Summary: Question generator for Slovak language
Home-page: https://github.com/mrshu/otazkovac
Author: Marek Suppa
Author-email: marek@suppa.sk
License: GPL 3.0
Keywords: question,generation,nlp
Platform: UNKNOWN
